setup.py
src/act_bb_usage/__init__.py
src/act_bb_usage/config.py
src/act_bb_usage/usage.py
src/act_bb_usage.egg-info/PKG-INFO
src/act_bb_usage.egg-info/SOURCES.txt
src/act_bb_usage.egg-info/dependency_links.txt
src/act_bb_usage.egg-info/entry_points.txt
src/act_bb_usage.egg-info/requires.txt
src/act_bb_usage.egg-info/top_level.txt