Metadata-Version: 1.1
Name: act-bb-usage
Version: 1.0
Summary: Fetch the total internet usage for the month
Home-page: https://github.com/lgp171188/act_bb_usage
Author: L. Guruprasad
Author-email: UNKNOWN
License: GPLv3
Platform: UNKNOWN
Classifier: Topic :: Utilities
Classifier: Operating System :: OS Independent
Classifier: Programming Language :: Python
Classifier: License :: OSI Approved :: GNU General Public License v3 (GPLv3)
